insutance/__init__.py
insutance/answer.py
insutance/command.py
insutance/main.py
insutance/question_data.py
insutance-0.0.3.dist-info/METADATA
insutance-0.0.3.dist-info/WHEEL
insutance-0.0.3.dist-info/entry_points.txt
insutance-0.0.3.dist-info/top_level.txt
insutance-0.0.3.dist-info/RECORD
