Metadata-Version: 2.1
Name: insutance
Version: 0.0.3
Summary: Hey insutance! Who are you?
Home-page: https://github.com/insutance/hey-insutance
Author: insutance
Author-email: insutance@naver.com
License: UNKNOWN
Platform: UNKNOWN
Requires-Python: >= 3.8
